{
    "threads": {
        "data-example-1": {
            "id": "data-example-1",
            "items": {
                "data-example-1-1": {
                    "id": "data-example-1-1",
                    "codes": [
                        "hello"
                    ]
                },
                "data-example-1-2": {
                    "id": "data-example-1-2",
                    "codes": [
                        "world"
                    ]
                }
            }
        }
    }
}
